genai_ocean/__init__.py
genai_ocean/embed_search.py
genai_ocean/html_parser.py
genai_ocean/search.py
genai_ocean/search_tool.py
genai_ocean-0.1.0.dist-info/LICENSE
genai_ocean-0.1.0.dist-info/METADATA
genai_ocean-0.1.0.dist-info/WHEEL
genai_ocean-0.1.0.dist-info/top_level.txt
genai_ocean-0.1.0.dist-info/RECORD
